smamp/__init__.py
smamp/aa2ua_cube.py
smamp/charges_to_rtp.py
smamp/convert_UA_to_AA.py
smamp/extract_bader_charges.py
smamp/insertHbyList.py
smamp/tools.py
smamp-1.7.dist-info/LICENSE
smamp-1.7.dist-info/METADATA
smamp-1.7.dist-info/WHEEL
smamp-1.7.dist-info/top_level.txt
smamp-1.7.dist-info/RECORD
