Metadata-Version: 2.1
Name: smamp
Version: 1.7
Summary: Self-consistently optimizing smamp charges.
Home-page: UNKNOWN
Author: Lukas Elflein
Author-email: elfleinl@tf.uni-freiburg.de
License: MIT
Platform: UNKNOWN
